LICENSE.txt
MANIFEST.in
README.rst
setup.py
DjangoRpc.egg-info/PKG-INFO
DjangoRpc.egg-info/SOURCES.txt
DjangoRpc.egg-info/dependency_links.txt
DjangoRpc.egg-info/top_level.txt
djangorpc/__init__.py
djangorpc/datastructures.py
djangorpc/decorators.py
djangorpc/exceptions.py
djangorpc/responses.py
djangorpc/router.py
djangorpc/settings.py
djangorpc/static/djangorpc/js/jquery-1.9.1.min.js
djangorpc/static/djangorpc/js/jquery.form.js
djangorpc/static/djangorpc/js/jquery.rpc.js
djangorpc/static/djangorpc/js/jquery.util.js
djangorpc/utils/__init__.py
djangorpc/utils/forms.py
docs/.gitignore
docs/Makefile
docs/conf.py
docs/example.rst
docs/index.rst
docs/installation.rst
docs/make.bat
docs/_static/.gitignore
docs/api/decorators.rst
docs/api/exceptions.rst
docs/api/index.rst
docs/api/responses.rst
docs/api/router.rst
docs/api/utils.rst
docs/tutorial/index.rst
docs/tutorial/part1.rst
docs/tutorial/part2.rst
docs/tutorial/part3.rst
docs/tutorial/part4.rst