Metadata-Version: 1.1
Name: DjangoRpc
Version: 0.4
Summary: Django RPC for jQuery
Home-page: https://django-rpc.readthedocs.org/
Author: Dmitriy Kostochko
Author-email: alerionum+django@gmail.com
License: The MIT License (MIT)
Keywords: Django,RPC,API,jQuery
Platform: UNKNOWN
Classifier: Environment :: Web Environment
Classifier: Framework :: Django
Classifier: Intended Audience :: Developers
Classifier: License :: OSI Approved :: MIT License
Classifier: Operating System :: OS Independent
Classifier: Programming Language :: Python
Classifier: Programming Language :: Python :: 2.6
Classifier: Programming Language :: Python :: 2.7
Classifier: Topic :: Internet :: WWW/HTTP
Classifier: Topic :: Internet :: WWW/HTTP :: Dynamic Content
